README.md
setup.cfg
setup.py
celebrity_births_Shweta_2021.egg-info/PKG-INFO
celebrity_births_Shweta_2021.egg-info/SOURCES.txt
celebrity_births_Shweta_2021.egg-info/dependency_links.txt
celebrity_births_Shweta_2021.egg-info/requires.txt
celebrity_births_Shweta_2021.egg-info/top_level.txt
project/__init__.py
project/date.py
project/example.py
project/scraper.py