Metadata-Version: 1.0
Name: celebrity-births-Shweta-2021
Version: 0.0.1
Summary: Mock package that allows you to find celebrity by date of birth
Home-page: https://github.com/shweta-29/Celebrities-Births.git
Author: Shweta Yadav
Author-email: UNKNOWN
License: MIT
Platform: UNKNOWN
